{
    "text": "Умираю от красоты в новой коллекции Khaite весна 2025. Нравится сочетание атласного шелка и блескучей кожи, шифон, жабо, дышащий трикотаж ручной работы. А как он сочетается с сумкой пэтчворк. А этот бежевый клатч из замши на лавандовом платье? А цветной бисер на босоножках в тотал-блэк луке? Считаю, это поэзия. \n\nЯ считаю, что Khaite — одно из главных явлений в современной моде. Да, вдохновение Олсен и Фиби иногда считывается явно, но именно как инспир. Кэтрин Гольштейн, которая все это придумывает, гениальная.\n\nА вот Alaïa новый мне не вау, прикиньте. Но это и в целом не мой бренд еще со времен самого Аззедина.",
    "date": "2024-09-09T11:18:50+00:00",
    "views": 4594,
    "forwards": 19,
    "reactions": {
        "_": "MessageReactions",
        "results": [
            {
                "_": "ReactionCount",
                "reaction": {
                    "_": "ReactionEmoji",
                    "emoticon": "❤"
                },
                "count": 114,
                "chosen_order": null
            },
            {
                "_": "ReactionCount",
                "reaction": {
                    "_": "ReactionEmoji",
                    "emoticon": "🔥"
                },
                "count": 31,
                "chosen_order": null
            },
            {
                "_": "ReactionCount",
                "reaction": {
                    "_": "ReactionEmoji",
                    "emoticon": "💯"
                },
                "count": 6,
                "chosen_order": null
            },
            {
                "_": "ReactionCount",
                "reaction": {
                    "_": "ReactionEmoji",
                    "emoticon": "🤩"
                },
                "count": 5,
                "chosen_order": null
            },
            {
                "_": "ReactionCount",
                "reaction": {
                    "_": "ReactionEmoji",
                    "emoticon": "👍"
                },
                "count": 1,
                "chosen_order": null
            }
        ],
        "min": false,
        "can_see_list": false,
        "reactions_as_tags": false,
        "recent_reactions": [],
        "top_reactors": []
    },
    "media": []
}