{
    "text": "Очень классная съемка с Сашей Пивоваровой в новом американском L’Officiel. \n\nНаши бренды обожают снимать кампейны в студии, на цикле или на бетонном полу, и я ничего против этого не имею. Но результат на процентов 60 зависит от модели. И очень мало кто может выдать столько классных эмоций, поз и превратить такие простые картинки в настоящую историю. \n\nНо здесь еще отдельный лайк за стилизацию.",
    "date": "2024-09-16T16:30:30+00:00",
    "views": 4086,
    "forwards": 19,
    "reactions": {
        "_": "MessageReactions",
        "results": [
            {
                "_": "ReactionCount",
                "reaction": {
                    "_": "ReactionEmoji",
                    "emoticon": "❤"
                },
                "count": 141,
                "chosen_order": null
            },
            {
                "_": "ReactionCount",
                "reaction": {
                    "_": "ReactionEmoji",
                    "emoticon": "🔥"
                },
                "count": 29,
                "chosen_order": null
            },
            {
                "_": "ReactionCount",
                "reaction": {
                    "_": "ReactionEmoji",
                    "emoticon": "👍"
                },
                "count": 17,
                "chosen_order": null
            },
            {
                "_": "ReactionCount",
                "reaction": {
                    "_": "ReactionEmoji",
                    "emoticon": "🍓"
                },
                "count": 3,
                "chosen_order": null
            }
        ],
        "min": false,
        "can_see_list": false,
        "reactions_as_tags": false,
        "recent_reactions": [],
        "top_reactors": []
    },
    "media": []
}