{
    "text": "Находки недели, на которые упал мой глаз:\n\n🔥 новая коллекция COS atelier, особенно понравились сумка и красные лодочки без каблука\n🔥 симпатичные ультра остроносые лодочки от 12storeez\n🔥 прям мое элегантное платье с драпировкой \n🔥 сумочка а-ля Magda Butrym в Befree\n🔥 эффектный топ с бахромой в Lime",
    "date": "2024-04-19T16:09:00+00:00",
    "views": 66169,
    "forwards": 87,
    "reactions": {
        "_": "MessageReactions",
        "results": [
            {
                "_": "ReactionCount",
                "reaction": {
                    "_": "ReactionEmoji",
                    "emoticon": "❤"
                },
                "count": 688,
                "chosen_order": null
            },
            {
                "_": "ReactionCount",
                "reaction": {
                    "_": "ReactionEmoji",
                    "emoticon": "🔥"
                },
                "count": 213,
                "chosen_order": null
            },
            {
                "_": "ReactionCount",
                "reaction": {
                    "_": "ReactionEmoji",
                    "emoticon": "👍"
                },
                "count": 173,
                "chosen_order": null
            },
            {
                "_": "ReactionCount",
                "reaction": {
                    "_": "ReactionEmoji",
                    "emoticon": "🥰"
                },
                "count": 23,
                "chosen_order": null
            },
            {
                "_": "ReactionCount",
                "reaction": {
                    "_": "ReactionEmoji",
                    "emoticon": "😢"
                },
                "count": 6,
                "chosen_order": null
            },
            {
                "_": "ReactionCount",
                "reaction": {
                    "_": "ReactionEmoji",
                    "emoticon": "🤔"
                },
                "count": 1,
                "chosen_order": null
            }
        ],
        "min": false,
        "can_see_list": false,
        "reactions_as_tags": false,
        "recent_reactions": [],
        "top_reactors": []
    },
    "media": [
        "parsing/telegram_parser/data\\mariannaeliseeva\\media\\1650.jpg",
        "parsing/telegram_parser/data\\mariannaeliseeva\\media\\1651.jpg"
    ],
    "media_clothing_score_CLIP_base": [
        [
            0.43092647194862366,
            "parsing/telegram_parser/data\\mariannaeliseeva\\media\\1650.jpg"
        ],
        [
            0.5752557516098022,
            "parsing/telegram_parser/data\\mariannaeliseeva\\media\\1651.jpg"
        ]
    ],
    "media_clothing_score_CLIP_large": [
        [
            0.11914825439453125,
            "parsing/telegram_parser/data\\mariannaeliseeva\\media\\1650.jpg"
        ],
        [
            0.3292255401611328,
            "parsing/telegram_parser/data\\mariannaeliseeva\\media\\1651.jpg"
        ]
    ]
}