{
    "text": "Кеды под bloke core (футбольная эстетика).  Вот выбираю. Из фаворитов Puma и Massimo Dutti с сеточкой ⚽️🥅 Архивные Prada была попытка поискать на Авито, но все в оооочень винтажном состоянии.",
    "date": "2024-04-21T15:11:21+00:00",
    "views": 67002,
    "forwards": 146,
    "reactions": {
        "_": "MessageReactions",
        "results": [
            {
                "_": "ReactionCount",
                "reaction": {
                    "_": "ReactionEmoji",
                    "emoticon": "❤"
                },
                "count": 684,
                "chosen_order": null
            },
            {
                "_": "ReactionCount",
                "reaction": {
                    "_": "ReactionEmoji",
                    "emoticon": "🔥"
                },
                "count": 172,
                "chosen_order": null
            },
            {
                "_": "ReactionCount",
                "reaction": {
                    "_": "ReactionEmoji",
                    "emoticon": "👍"
                },
                "count": 154,
                "chosen_order": null
            },
            {
                "_": "ReactionCount",
                "reaction": {
                    "_": "ReactionEmoji",
                    "emoticon": "🤔"
                },
                "count": 61,
                "chosen_order": null
            },
            {
                "_": "ReactionCount",
                "reaction": {
                    "_": "ReactionEmoji",
                    "emoticon": "❤‍🔥"
                },
                "count": 16,
                "chosen_order": null
            },
            {
                "_": "ReactionCount",
                "reaction": {
                    "_": "ReactionEmoji",
                    "emoticon": "😢"
                },
                "count": 11,
                "chosen_order": null
            },
            {
                "_": "ReactionCount",
                "reaction": {
                    "_": "ReactionEmoji",
                    "emoticon": "🥰"
                },
                "count": 8,
                "chosen_order": null
            },
            {
                "_": "ReactionCount",
                "reaction": {
                    "_": "ReactionEmoji",
                    "emoticon": "😁"
                },
                "count": 6,
                "chosen_order": null
            },
            {
                "_": "ReactionCount",
                "reaction": {
                    "_": "ReactionEmoji",
                    "emoticon": "🤯"
                },
                "count": 5,
                "chosen_order": null
            },
            {
                "_": "ReactionCount",
                "reaction": {
                    "_": "ReactionEmoji",
                    "emoticon": "💯"
                },
                "count": 2,
                "chosen_order": null
            }
        ],
        "min": false,
        "can_see_list": false,
        "reactions_as_tags": false,
        "recent_reactions": [],
        "top_reactors": []
    },
    "media": [
        "parsing/telegram_parser/data\\mariannaeliseeva\\media\\1658.jpg"
    ],
    "media_clothing_score_CLIP_base": [
        [
            0.6877840161323547,
            "parsing/telegram_parser/data\\mariannaeliseeva\\media\\1658.jpg"
        ]
    ],
    "media_clothing_score_CLIP_large": [
        [
            0.8998193144798279,
            "parsing/telegram_parser/data\\mariannaeliseeva\\media\\1658.jpg"
        ]
    ]
}