{
    "text": "Роскошный камерный ужин устроили вчера Ekonika и новый амбассадор премиальной линейки бренда Оксана Рим. \n\nНи с одной из девушек не была знакома лично. Но от этого еще увлекательнее проходила беседа (местами даже бурная дискуссия). И японский ресторан JUN - открытие для меня🥢",
    "date": "2024-06-20T16:24:16+00:00",
    "views": 72195,
    "forwards": 47,
    "reactions": {
        "_": "MessageReactions",
        "results": [
            {
                "_": "ReactionCount",
                "reaction": {
                    "_": "ReactionEmoji",
                    "emoticon": "❤"
                },
                "count": 853,
                "chosen_order": null
            },
            {
                "_": "ReactionCount",
                "reaction": {
                    "_": "ReactionEmoji",
                    "emoticon": "🔥"
                },
                "count": 211,
                "chosen_order": null
            },
            {
                "_": "ReactionCount",
                "reaction": {
                    "_": "ReactionEmoji",
                    "emoticon": "👍"
                },
                "count": 165,
                "chosen_order": null
            },
            {
                "_": "ReactionCount",
                "reaction": {
                    "_": "ReactionEmoji",
                    "emoticon": "😍"
                },
                "count": 43,
                "chosen_order": null
            },
            {
                "_": "ReactionCount",
                "reaction": {
                    "_": "ReactionEmoji",
                    "emoticon": "❤‍🔥"
                },
                "count": 11,
                "chosen_order": null
            }
        ],
        "min": false,
        "can_see_list": false,
        "reactions_as_tags": false,
        "recent_reactions": [],
        "top_reactors": []
    },
    "media": []
}