{
    "text": "Помните заколки Lime из влога? Вот наткнулась на хочумогу. Шорты в ту же рубрику. Из интересного для меня - браслет на плечо. Возьму, посмотрю, как сидит.",
    "date": "2024-06-22T09:29:34+00:00",
    "views": 69321,
    "forwards": 81,
    "reactions": {
        "_": "MessageReactions",
        "results": [
            {
                "_": "ReactionCount",
                "reaction": {
                    "_": "ReactionEmoji",
                    "emoticon": "❤"
                },
                "count": 804,
                "chosen_order": null
            },
            {
                "_": "ReactionCount",
                "reaction": {
                    "_": "ReactionEmoji",
                    "emoticon": "🔥"
                },
                "count": 203,
                "chosen_order": null
            },
            {
                "_": "ReactionCount",
                "reaction": {
                    "_": "ReactionEmoji",
                    "emoticon": "👍"
                },
                "count": 167,
                "chosen_order": null
            },
            {
                "_": "ReactionCount",
                "reaction": {
                    "_": "ReactionEmoji",
                    "emoticon": "😍"
                },
                "count": 35,
                "chosen_order": null
            },
            {
                "_": "ReactionCount",
                "reaction": {
                    "_": "ReactionEmoji",
                    "emoticon": "❤‍🔥"
                },
                "count": 21,
                "chosen_order": null
            },
            {
                "_": "ReactionCount",
                "reaction": {
                    "_": "ReactionEmoji",
                    "emoticon": "🤔"
                },
                "count": 13,
                "chosen_order": null
            },
            {
                "_": "ReactionCount",
                "reaction": {
                    "_": "ReactionEmoji",
                    "emoticon": "😁"
                },
                "count": 2,
                "chosen_order": null
            }
        ],
        "min": false,
        "can_see_list": false,
        "reactions_as_tags": false,
        "recent_reactions": [],
        "top_reactors": []
    },
    "media": []
}