{
    "text": "А это история о том, как брючный костюм из ROGOVSHOP.RU стал частью воспоминаний одного учительского коллектива и их учеников. На фото вы видите реальных преподавателей одного из московских детских садов. Проект придумал и реализовал мой друг Паша Компан для своих детей, чтобы, как он сам выразился, у них был крутой «человеческий выпускной альбом». Мне кажется, что вышло очень круто!!!\nПаша, ты большой молодец и я рад быть частью такой классной инициативы!\nВсех с первым учебным днём! 🍂🤎🥇\n\nКстати, над проектом работали лучшие специалисты страны:\n\nПРОДЮСЕР И АРТ-ДИРЕКТОР: Павел Компан \nВОЛОСЫ: Марина Рой \nМАКИЯЖ: Алёна Моисеева \nФОТОГРАФ: Соня Сивакова\nОРГ: Ольга Закатова",
    "date": "2024-09-02T13:51:01+00:00",
    "views": 52849,
    "forwards": 152,
    "reactions": {
        "_": "MessageReactions",
        "results": [
            {
                "_": "ReactionCount",
                "reaction": {
                    "_": "ReactionEmoji",
                    "emoticon": "❤"
                },
                "count": 1091,
                "chosen_order": null
            },
            {
                "_": "ReactionCount",
                "reaction": {
                    "_": "ReactionEmoji",
                    "emoticon": "🔥"
                },
                "count": 549,
                "chosen_order": null
            },
            {
                "_": "ReactionCount",
                "reaction": {
                    "_": "ReactionEmoji",
                    "emoticon": "👍"
                },
                "count": 202,
                "chosen_order": null
            },
            {
                "_": "ReactionCount",
                "reaction": {
                    "_": "ReactionEmoji",
                    "emoticon": "🥰"
                },
                "count": 43,
                "chosen_order": null
            },
            {
                "_": "ReactionCount",
                "reaction": {
                    "_": "ReactionEmoji",
                    "emoticon": "👏"
                },
                "count": 16,
                "chosen_order": null
            },
            {
                "_": "ReactionCount",
                "reaction": {
                    "_": "ReactionEmoji",
                    "emoticon": "🤯"
                },
                "count": 13,
                "chosen_order": null
            },
            {
                "_": "ReactionCount",
                "reaction": {
                    "_": "ReactionEmoji",
                    "emoticon": "🎉"
                },
                "count": 12,
                "chosen_order": null
            },
            {
                "_": "ReactionCount",
                "reaction": {
                    "_": "ReactionEmoji",
                    "emoticon": "😢"
                },
                "count": 9,
                "chosen_order": null
            },
            {
                "_": "ReactionCount",
                "reaction": {
                    "_": "ReactionEmoji",
                    "emoticon": "😁"
                },
                "count": 8,
                "chosen_order": null
            }
        ],
        "min": false,
        "can_see_list": false,
        "reactions_as_tags": false,
        "recent_reactions": [],
        "top_reactors": []
    },
    "media": []
}